{
  "properties": {
    "filename": {
      "type": "search_as_you_type",
      "fields": {
        "keyword": {
          "type": "constant_keyword"
        }
      }
    },
    "content": {
      "type": "text"
    },
    "tokens": {
      "type": "keyword"
    },
    "token_character_offsets": {
      "type": "integer_range"
    },
    "keywords": {
      "type": "keyword"
    },
    "sdoc_id": {
      "type": "long"
    },
    "project_id": {
      "type": "long"
    },
    "created": {
      "type": "date"
    }
  }
}